{
  "key": "group_632bf826d42ce",
  "title": "Layout - Case Studies",
  "fields": [
    {
      "key": "field_632bf826e34fb",
      "label": "Content Settings",
      "name": "",
      "type": "tab",
      "instructions": "",
      "required": 0,
      "conditional_logic": 0,
      "wrapper": {
        "width": "",
        "class": "",
        "id": ""
      },
      "placement": "top",
      "endpoint": 0
    },
    {
      "key": "field_632bf8ed8a2bf",
      "label": "(Column 9\/12)",
      "name": "",
      "type": "acfe_column",
      "instructions": "",
      "required": 0,
      "conditional_logic": 0,
      "wrapper": {
        "width": "",
        "class": "",
        "id": ""
      },
      "acfe_permissions": "",
      "columns": "9\/12",
      "endpoint": 0
    },
    {
      "key": "field_632bf826e3508",
      "label": "Heading",
      "name": "heading",
      "type": "clone",
      "instructions": "",
      "required": 0,
      "conditional_logic": 0,
      "wrapper": {
        "width": "",
        "class": "",
        "id": ""
      },
      "acfe_permissions": "",
      "clone": [
        "group_62a1c763d7c90"
      ],
      "display": "group",
      "layout": "block",
      "prefix_label": 0,
      "prefix_name": 0,
      "acfe_seamless_style": 0,
      "acfe_clone_modal": 0,
      "acfe_settings": "",
      "acfe_clone_modal_close": 0,
      "acfe_clone_modal_button": "",
      "acfe_clone_modal_size": "large"
    },
    {
      "key": "field_632bf826e351f",
      "label": "Description",
      "name": "description",
      "type": "clone",
      "instructions": "",
      "required": 0,
      "conditional_logic": 0,
      "wrapper": {
        "width": "",
        "class": "",
        "id": ""
      },
      "acfe_permissions": "",
      "clone": [
        "group_62a2107ccfb06"
      ],
      "display": "group",
      "layout": "block",
      "prefix_label": 0,
      "prefix_name": 0,
      "acfe_seamless_style": 0,
      "acfe_clone_modal": 0,
      "acfe_settings": "",
      "acfe_clone_modal_close": 0,
      "acfe_clone_modal_button": "",
      "acfe_clone_modal_size": "large"
    },
    {
      "key": "field_632bf9008a2c0",
      "label": "(Column 2\/12)",
      "name": "",
      "type": "acfe_column",
      "instructions": "",
      "required": 0,
      "conditional_logic": 0,
      "wrapper": {
        "width": "",
        "class": "",
        "id": ""
      },
      "acfe_permissions": "",
      "columns": "2\/12",
      "endpoint": 0
    },
    {
      "key": "field_632bf8948a2bd",
      "label": "Show Search Bar",
      "name": "show_search_bar",
      "type": "true_false",
      "instructions": "",
      "required": 0,
      "conditional_logic": 0,
      "wrapper": {
        "width": "",
        "class": "",
        "id": ""
      },
      "acfe_permissions": "",
      "message": "",
      "default_value": 1,
      "ui": 1,
      "ui_on_text": "Show",
      "ui_off_text": "Hide",
      "acfe_settings": "",
      "acfe_validate": ""
    },
    {
      "key": "field_632bf8c58a2be",
      "label": "Show Filter Nav",
      "name": "show_filter_nav",
      "type": "true_false",
      "instructions": "",
      "required": 0,
      "conditional_logic": 0,
      "wrapper": {
        "width": "",
        "class": "",
        "id": ""
      },
      "acfe_permissions": "",
      "message": "",
      "default_value": 1,
      "ui": 1,
      "ui_on_text": "Show",
      "ui_off_text": "Hide",
      "acfe_settings": "",
      "acfe_validate": ""
    },
    {
      "key": "field_637271fd46973",
      "label": "Limit by Category",
      "name": "limit_by_category",
      "type": "taxonomy",
      "instructions": "",
      "required": 0,
      "conditional_logic": 0,
      "wrapper": {
        "width": "",
        "class": "",
        "id": ""
      },
      "acfe_permissions": "",
      "taxonomy": "impact_category",
      "field_type": "checkbox",
      "add_term": 0,
      "save_terms": 0,
      "load_terms": 0,
      "return_format": "id",
      "acfe_bidirectional": {
        "acfe_bidirectional_enabled": "0"
      },
      "acfe_settings": "",
      "acfe_validate": "",
      "multiple": 0,
      "allow_null": 0
    },
    {
      "key": "field_636a0a7e9403d",
      "label": "Show # of Posts",
      "name": "posts_per_page",
      "type": "number",
      "instructions": "",
      "required": 0,
      "conditional_logic": 0,
      "wrapper": {
        "width": "",
        "class": "",
        "id": ""
      },
      "acfe_permissions": "",
      "default_value": 9,
      "placeholder": "",
      "prepend": "",
      "append": "",
      "min": "",
      "max": "",
      "step": "",
      "acfe_settings": "",
      "acfe_validate": ""
    },
    {
      "key": "field_632bf90f8a2c1",
      "label": "(Column Endpoint)",
      "name": "",
      "type": "acfe_column",
      "instructions": "",
      "required": 0,
      "conditional_logic": 0,
      "wrapper": {
        "width": "",
        "class": "",
        "id": ""
      },
      "acfe_permissions": "",
      "endpoint": 1,
      "columns": "6\/12"
    },
    {
      "key": "field_632bf826e354e",
      "label": "Section Settings",
      "name": "",
      "type": "tab",
      "instructions": "",
      "required": 0,
      "conditional_logic": 0,
      "wrapper": {
        "width": "",
        "class": "",
        "id": ""
      },
      "placement": "top",
      "endpoint": 0
    },
    {
      "key": "field_632bf826e3565",
      "label": "Section Settings",
      "name": "section_settings",
      "type": "clone",
      "instructions": "",
      "required": 0,
      "conditional_logic": 0,
      "wrapper": {
        "width": "",
        "class": "",
        "id": ""
      },
      "clone": [
        "group_629ecb2c781f6"
      ],
      "display": "group",
      "layout": "row",
      "prefix_label": 0,
      "prefix_name": 0,
      "acfe_seamless_style": 1,
      "acfe_clone_modal": 0,
      "acfe_clone_modal_close": 0,
      "acfe_clone_modal_button": "",
      "acfe_clone_modal_size": "large"
    }
  ],
  "location": [
    [
      {
        "param": "post_type",
        "operator": "==",
        "value": "page"
      }
    ]
  ],
  "menu_order": 0,
  "position": "normal",
  "style": "default",
  "label_placement": "left",
  "instruction_placement": "field",
  "hide_on_screen": "",
  "active": false,
  "description": "",
  "show_in_rest": 0,
  "acfe_display_title": "",
  "acfe_autosync": [
    "json"
  ],
  "acfe_permissions": "",
  "acfe_form": 1,
  "acfe_meta": "",
  "acfe_note": "",
  "modified": 1668444700,
  "acfe_categories": {
    "layout": "Layout"
  }
}